{"name":"Malfunctioning Repair Drone","traits":"Uncommon, Robot, Tech","tags":[],"level":0,"specials":[{"id":"_1a4g6n0zksd","name":"Construct Armor","traits":"","range":"","actions":"none","type":"defense","description":"Like normal objects, this robot has Hardness. This Hardness reduces any damage it takes by an amount equal to the Hardness. Once this robot is reduced to less than half its Hit Points, or immediately upon being damaged by a critical hit, its construct armor breaks and its Armor Class is reduced to 13."}],"morespells":[],"alignment":"n","size":"medium","type":"construct","adjust":0,"description":"","items":"","spellattack":{"value":"","benchmark":"moderate","note":""},"spelldc":{"value":"","benchmark":"moderate","note":""},"savenote":"","creature":"","speed":"25 feet","imgurl":"","spelltype":"","focuspoints":0,"cantriplevel":"","ritualtype":"","rituals":"","spells":["","","","","","","","","","",""],"constant":"","minprof":{"value":"","benchmark":"moderate","note":""},"strength":{"value":"+3","benchmark":"high","note":""},"dexterity":{"value":"+0","benchmark":"low","note":""},"constitution":{"value":"+2","benchmark":"moderate","note":""},"intelligence":{"value":0,"benchmark":"moderate","note":""},"wisdom":{"value":"+0","benchmark":"low","note":""},"charisma":{"value":"-5","benchmark":"abysmal","note":""},"perception":{"value":"+3","benchmark":"low","note":"darkvision"},"acrobatics":{"value":"","benchmark":"moderate","note":""},"arcana":{"value":"","benchmark":"moderate","note":""},"athletics":{"value":"+6","benchmark":"high","note":""},"crafting":{"value":"","benchmark":"moderate","note":""},"deception":{"value":"","benchmark":"moderate","note":""},"diplomacy":{"value":"","benchmark":"moderate","note":""},"intimidation":{"value":"","benchmark":"moderate","note":""},"medicine":{"value":"","benchmark":"moderate","note":""},"nature":{"value":"","benchmark":"moderate","note":""},"occultism":{"value":"","benchmark":"moderate","note":""},"performance":{"value":"","benchmark":"moderate","note":""},"religion":{"value":"","benchmark":"moderate","note":""},"society":{"value":"","benchmark":"moderate","note":""},"stealth":{"value":"","benchmark":"moderate","note":""},"survival":{"value":"","benchmark":"moderate","note":""},"thievery":{"value":"+5","benchmark":"moderate","note":""},"lore":{"value":"+3","benchmark":"low","note":"","name":"Engineering Lore"},"lorealt":{"value":"","benchmark":"moderate","note":"","name":"lore"},"ac":{"value":"15","benchmark":"high","note":"construct armor"},"hp":{"value":15,"benchmark":"moderate","note":"Hardness 2"},"fortitude":{"value":"+1","benchmark":"terrible","note":""},"reflex":{"value":"+3","benchmark":"low","note":""},"will":{"value":"+1","benchmark":"terrible","note":""},"resistance":{"value":"","benchmark":"moderate","note":""},"weakness":{"value":"electricity 5","benchmark":"moderate","note":""},"immunity":{"value":"bleed, death effects, diseased, doomed, drained, fatigued, healing, necromancy, nonlethal attacks, paralyzed, poison, sickened, unconscious","benchmark":"moderate","note":""},"roadmap":"","info":"","strikes":[{"id":"_1xwx9l484mm","name":"slam","traits":"","attack":"+4","damage":"1d4+1 bludgeoning","type":"Melee"}],"languages":"Androffan"}